sqlsl/__init__.py
sqlsl/main.py
sqlsl-0.1.0.dist-info/LICENSE
sqlsl-0.1.0.dist-info/WHEEL
sqlsl-0.1.0.dist-info/METADATA
sqlsl-0.1.0.dist-info/RECORD
