Metadata-Version: 2.1
Name: sqlsl
Version: 0.1.0
Summary: SQL simple loader
Home-page: https://github.com/pegov/sqlsl
License: MIT
Keywords: sql
Author: pegov
Requires-Python: >=3.7,<4.0
Classifier: License :: OSI Approved :: MIT License
Classifier: Programming Language :: Python :: 3
Classifier: Programming Language :: Python :: 3.10
Classifier: Programming Language :: Python :: 3.7
Classifier: Programming Language :: Python :: 3.8
Classifier: Programming Language :: Python :: 3.9
Project-URL: Repository, https://github.com/pegov/sqlsl
